VisualiseKerasLayers/Visualise.py
VisualiseKerasLayers/__init__.py
VisualiseKerasLayers-1.1.dist-info/METADATA
VisualiseKerasLayers-1.1.dist-info/WHEEL
VisualiseKerasLayers-1.1.dist-info/top_level.txt
VisualiseKerasLayers-1.1.dist-info/RECORD
