Metadata-Version: 2.1
Name: VisualiseKerasLayers
Version: 1.1
Summary: Package to generating plots with visualised activations of model layers
Home-page: UNKNOWN
Author: Matt Kozlowski
Author-email: mateusz.a.kozlowski@gmail.com
License: MIT
Platform: UNKNOWN
